odoo/addons/sale_stock_on_hand_popup/README.rst
odoo/addons/sale_stock_on_hand_popup/__init__.py
odoo/addons/sale_stock_on_hand_popup/__manifest__.py
odoo/addons/sale_stock_on_hand_popup/i18n/it.po
odoo/addons/sale_stock_on_hand_popup/i18n/sale_stock_on_hand_popup.pot
odoo/addons/sale_stock_on_hand_popup/models/__init__.py
odoo/addons/sale_stock_on_hand_popup/models/product_product.py
odoo/addons/sale_stock_on_hand_popup/models/res_config_settings.py
odoo/addons/sale_stock_on_hand_popup/readme/CONTRIBUTORS.rst
odoo/addons/sale_stock_on_hand_popup/readme/DESCRIPTION.rst
odoo/addons/sale_stock_on_hand_popup/readme/USAGE.rst
odoo/addons/sale_stock_on_hand_popup/security/ir.model.access.csv
odoo/addons/sale_stock_on_hand_popup/security/security.xml
odoo/addons/sale_stock_on_hand_popup/static/description/icon.png
odoo/addons/sale_stock_on_hand_popup/static/description/index.html
odoo/addons/sale_stock_on_hand_popup/static/src/js/stock_on_hand_widget.js
odoo/addons/sale_stock_on_hand_popup/static/src/xml/stock_on_hand_widget.xml
odoo/addons/sale_stock_on_hand_popup/tests/__init__.py
odoo/addons/sale_stock_on_hand_popup/tests/test_sale_stock_on_hand_popup.py
odoo/addons/sale_stock_on_hand_popup/views/assets.xml
odoo/addons/sale_stock_on_hand_popup/views/res_config_settings_views.xml
odoo/addons/sale_stock_on_hand_popup/views/sale_order_views.xml
odoo/addons/sale_stock_on_hand_popup/wizards/__init__.py
odoo/addons/sale_stock_on_hand_popup/wizards/product_quant_wizard.py
odoo/addons/sale_stock_on_hand_popup/wizards/product_quant_wizard_views.xml
odoo14_addon_sale_stock_on_hand_popup-14.0.2.0.1.dist-info/METADATA
odoo14_addon_sale_stock_on_hand_popup-14.0.2.0.1.dist-info/WHEEL
odoo14_addon_sale_stock_on_hand_popup-14.0.2.0.1.dist-info/top_level.txt
odoo14_addon_sale_stock_on_hand_popup-14.0.2.0.1.dist-info/RECORD
