Metadata-Version: 2.1
Name: odoo14-addon-sale_stock_on_hand_popup
Version: 14.0.2.0.1
Summary: Sale Stock On Hand Popup
Home-page: https://github.com/OCA/stock-logistics-warehouse
Author: PyTech SRL, Ooops404, Odoo Community Association (OCA)
Author-email: support@odoo-community.org
License: AGPL-3
Classifier: Programming Language :: Python
Classifier: Framework :: Odoo
Classifier: Framework :: Odoo :: 14.0
Classifier: License :: OSI Approved :: GNU Affero General Public License v3
Requires-Python: >=3.6
Requires-Dist: odoo14-addon-stock-available
Requires-Dist: odoo<14.1dev,>=14.0a
